[
    {
        "id": "684064a909a144eda75c36e0a2ebd196",
        "title": "The awkward",
        "content": "The awkward content",
        "author": "Ich",
        "date": "2024-08-15T08:33:48.194239",
        "comments": [],
        "categories": [],
        "tags": []
    },
    {
        "id": "17ea93e9b6074f469465d75a64c1c637",
        "title": "Love",
        "content": "Liebeserkl\u00e4rung",
        "author": "Your Name",
        "date": "2024-08-15T20:26:08.274908+00:00",
        "comments": [],
        "categories": [],
        "tags": []
    },
    {
        "id": "ed7acb4bc8c642fc98ad84ac8de17da5",
        "title": "dwad",
        "content": "dwadwad",
        "author": "Alex",
        "date": "2024-08-15T20:34:12.711963+00:00",
        "comments": [],
        "categories": [],
        "tags": []
    }
]